l2x_synthetic/__init__.py
l2x_synthetic/make_data.py
l2x_synthetic/make_data_test.py
l2x_synthetic-2.0.1.dist-info/METADATA
l2x_synthetic-2.0.1.dist-info/WHEEL
l2x_synthetic-2.0.1.dist-info/top_level.txt
l2x_synthetic-2.0.1.dist-info/RECORD
