Metadata-Version: 2.1
Name: l2x-synthetic
Version: 2.0.1
Summary: 4 simple customizable synthetic datasets from Chen et al., 2018 (L2X): Orange Skin, XOR, Non-linear Additive and Switch.
Home-page: https://github.com/dunnkers/L2X
Author: Jianbo Chen. Distributed by Jeroen Overschie.
License: MIT
Platform: UNKNOWN
Requires-Dist: numpy (>=1.19)
Requires-Dist: pandas (>=1.1)
